fidelior/__init__.py
fidelior/core.py
fidelior-0.7.5.dist-info/LICENSE
fidelior-0.7.5.dist-info/METADATA
fidelior-0.7.5.dist-info/WHEEL
fidelior-0.7.5.dist-info/top_level.txt
fidelior-0.7.5.dist-info/RECORD
