Metadata-Version: 2.1
Name: fidelior
Version: 0.7.5
Summary: FIDELIOR: FInite-Difference-Equation LInear OperatoR package
Home-page: https://gitlab.com/nleht/fidelior
Author: Nikolai G. Lehtinen
Author-email: nlehtinen@gmail.com
License: CC BY-ND 4.0
Keywords: finite-difference equations,partial differential equations
License-File: LICENSE
Requires-Dist: numpy (>=1.14.0)
Requires-Dist: scipy (>=1.0.0)
